fcapacity_management/__init__.py
fcapacity_management/capacity_status.py
fcapacity_management/operation.py
fcapacity_mngmt-2.5.dist-info/METADATA
fcapacity_mngmt-2.5.dist-info/WHEEL
fcapacity_mngmt-2.5.dist-info/top_level.txt
fcapacity_mngmt-2.5.dist-info/RECORD
